app_creator/__init__.py
app_creator/cli.py
migrations/__init__.py
models/__init__.py
views/__init__.py
django_app_creator-1.0.0.dist-info/METADATA
django_app_creator-1.0.0.dist-info/WHEEL
django_app_creator-1.0.0.dist-info/entry_points.txt
django_app_creator-1.0.0.dist-info/top_level.txt
django_app_creator-1.0.0.dist-info/RECORD
