Metadata-Version: 2.4
Name: django-app-creator
Version: 1.0.0
Summary: Générateur de structure d'app Django personnalisée
Author: kamax
Author-email: blab97400@gmail.com
License: MIT
Classifier: Programming Language :: Python :: 3
Classifier: Framework :: Django
Classifier: License :: OSI Approved :: MIT License
Dynamic: author
Dynamic: author-email
Dynamic: classifier
Dynamic: description
Dynamic: description-content-type
Dynamic: license
Dynamic: summary
